bn_lightweight_charts/__init__.py
bn_lightweight_charts/abstract.py
bn_lightweight_charts/chart.py
bn_lightweight_charts/drawings.py
bn_lightweight_charts/polygon.py
bn_lightweight_charts/table.py
bn_lightweight_charts/toolbox.py
bn_lightweight_charts/topbar.py
bn_lightweight_charts/util.py
bn_lightweight_charts/widgets.py
bn_lightweight_charts/js/bundle.js
bn_lightweight_charts/js/index.html
bn_lightweight_charts/js/index_bn.html
bn_lightweight_charts/js/lightweight-charts.js
bn_lightweight_charts/js/styles.css
bn_lightweight_charts-1.1.0.dist-info/METADATA
bn_lightweight_charts-1.1.0.dist-info/WHEEL
bn_lightweight_charts-1.1.0.dist-info/licenses/LICENSE
bn_lightweight_charts-1.1.0.dist-info/RECORD
