Metadata-Version: 2.4
Name: bn-lightweight-charts
Version: 1.1.0
Summary: Python framework for TradingView's Lightweight Charts JavaScript library.
Project-URL: Homepage, https://github.com/smalinin/bn_lightweight-charts-python
Project-URL: Source, https://github.com/smalinin/bn_lightweight-charts-python
Author: smalinin
License: MIT
License-File: LICENSE
Classifier: Development Status :: 5 - Production/Stable
Classifier: License :: OSI Approved :: MIT License
Classifier: Operating System :: OS Independent
Classifier: Programming Language :: Python :: 3
Requires-Python: >=3.8
Requires-Dist: pandas
Requires-Dist: tzlocal
